pydiffres/__init__.py
pydiffres/core.py
pydiffres/diffres.py
pydiffres/pooling.py
pydiffres-0.0.1.dist-info/METADATA
pydiffres-0.0.1.dist-info/WHEEL
pydiffres-0.0.1.dist-info/top_level.txt
pydiffres-0.0.1.dist-info/RECORD
