Metadata-Version: 2.1
Name: pydiffres
Version: 0.0.1
Summary: This package is written for learning adaptive resolution of time series data.
Home-page: https://github.com/haoheliu/diffres-python
Author: Haohe Liu
Author-email: haoheliu@gmail.com
License: MIT
Platform: UNKNOWN
Classifier: License :: OSI Approved :: MIT License
Classifier: Programming Language :: Python
Classifier: Programming Language :: Python :: 3
Classifier: Programming Language :: Python :: 3.7
Classifier: Programming Language :: Python :: Implementation :: CPython
Classifier: Programming Language :: Python :: Implementation :: PyPy
Requires-Python: >=3.6.0
Requires-Dist: torch (>=1.8.0)
Requires-Dist: matplotlib
